[
  {
    "line": 2,
    "elements": [
      {
        "start_timestamp": "2020-06-18T22:47:26.548Z",
        "before": [
          {
            "result": {
              "duration": 4399000000,
              "status": "passed"
            },
            "match": {
              "location": "stepDefinations.stepdefination.init()"
            }
          }
        ],
        "line": 3,
        "name": "User should be able to change the setting",
        "description": "",
        "id": "user-setting;user-should-be-able-to-change-the-setting",
        "after": [
          {
            "result": {
              "duration": 929000000,
              "status": "passed"
            },
            "match": {
              "location": "stepDefinations.stepdefination.tearDown()"
            }
          }
        ],
        "type": "scenario",
        "keyword": "Scenario",
        "steps": [
          {
            "result": {
              "duration": 5005000000,
              "status": "passed"
            },
            "line": 4,
            "name": "I opened the \"baseURL\"",
            "match": {
              "arguments": [
                {
                  "val": "\"baseURL\"",
                  "offset": 13
                }
              ],
              "location": "stepDefinations.stepdefination.i_opened_the(java.lang.String)"
            },
            "keyword": "Given "
          },
          {
            "result": {
              "duration": 403000000,
              "status": "passed"
            },
            "line": 5,
            "name": "I entered login details",
            "match": {
              "location": "stepDefinations.stepdefination.i_entered_login_details()"
            },
            "keyword": "And "
          },
          {
            "result": {
              "duration": 1808000000,
              "status": "passed"
            },
            "line": 6,
            "name": "I clicked on \"Einstellungen\"",
            "match": {
              "arguments": [
                {
                  "val": "\"Einstellungen\"",
                  "offset": 13
                }
              ],
              "location": "stepDefinations.stepdefination.i_clicked_on(java.lang.String)"
            },
            "keyword": "And "
          },
          {
            "result": {
              "duration": 1184000000,
              "status": "passed"
            },
            "line": 7,
            "name": "I clicked on \"Benutzereinstellungen\"",
            "match": {
              "arguments": [
                {
                  "val": "\"Benutzereinstellungen\"",
                  "offset": 13
                }
              ],
              "location": "stepDefinations.stepdefination.i_clicked_on(java.lang.String)"
            },
            "keyword": "And "
          },
          {
            "result": {
              "duration": 273000000,
              "status": "passed"
            },
            "line": 8,
            "name": "I select \"QS\" from select list",
            "match": {
              "arguments": [
                {
                  "val": "\"QS\"",
                  "offset": 9
                }
              ],
              "location": "stepDefinations.stepdefination.i_select_from_select_list(java.lang.String)"
            },
            "keyword": "Then "
          },
          {
            "result": {
              "duration": 399000000,
              "status": "passed"
            },
            "line": 9,
            "name": "I select \"Laufwege\" as a radio button",
            "match": {
              "arguments": [
                {
                  "val": "\"Laufwege\"",
                  "offset": 9
                }
              ],
              "location": "stepDefinations.stepdefination.i_select_as_a_radio_button(java.lang.String)"
            },
            "keyword": "Then "
          },
          {
            "result": {
              "duration": 219000000,
              "status": "passed"
            },
            "line": 10,
            "name": "I click On save button",
            "match": {
              "location": "stepDefinations.stepdefination.i_click_On_save_button()"
            },
            "keyword": "And "
          },
          {
            "result": {
              "duration": 239000000,
              "status": "passed"
            },
            "line": 11,
            "name": "I clicked on logout Button",
            "match": {
              "location": "stepDefinations.stepdefination.i_clicked_on_logout_Button()"
            },
            "keyword": "Then "
          },
          {
            "result": {
              "duration": 1439000000,
              "status": "passed"
            },
            "line": 12,
            "name": "I entered login details",
            "match": {
              "location": "stepDefinations.stepdefination.i_entered_login_details()"
            },
            "keyword": "And "
          },
          {
            "result": {
              "duration": 259000000,
              "status": "passed"
            },
            "line": 13,
            "name": "I verified Laufwege is Active in table",
            "match": {
              "location": "stepDefinations.stepdefination.i_verified_is_Active_in_table()"
            },
            "keyword": "Then "
          }
        ],
        "tags": [
          {
            "name": "@tc1"
          }
        ]
      }
    ],
    "name": "User Setting",
    "description": "",
    "id": "user-setting",
    "keyword": "Feature",
    "uri": "file:src/test/java/features/UserSetting.feature",
    "tags": [
      {
        "name": "@tc1",
        "type": "Tag",
        "location": {
          "line": 1,
          "column": 1
        }
      }
    ]
  }
]